README
setup.py
olegdb/__init__.py
olegdb/oleg.py
olegdb_python.egg-info/PKG-INFO
olegdb_python.egg-info/SOURCES.txt
olegdb_python.egg-info/dependency_links.txt
olegdb_python.egg-info/not-zip-safe
olegdb_python.egg-info/requires.txt
olegdb_python.egg-info/top_level.txt