Metadata-Version: 1.0
Name: olegdb-python
Version: 0.1.5
Summary: Python wrappers for generic OlegDB methods.
Home-page: https://github.com/infoforcefeed/olegdb-python
Author: Quinlan Pfiffer
Author-email: qpfiffer@gmail.com
License: BSD
Keywords: OlegDB
Platform: UNKNOWN
